vectorvein-0.3.68.dist-info/METADATA
vectorvein-0.3.68.dist-info/WHEEL
vectorvein-0.3.68.dist-info/entry_points.txt
vectorvein/__init__.py
vectorvein/api/__init__.py
vectorvein/api/access_key.py
vectorvein/api/agent_workspace.py
vectorvein/api/base.py
vectorvein/api/client.py
vectorvein/api/exceptions.py
vectorvein/api/file_upload.py
vectorvein/api/models.py
vectorvein/api/task_agent.py
vectorvein/api/workflow.py
vectorvein/chat_clients/__init__.py
vectorvein/chat_clients/anthropic_client.py
vectorvein/chat_clients/baichuan_client.py
vectorvein/chat_clients/base_client.py
vectorvein/chat_clients/deepseek_client.py
vectorvein/chat_clients/ernie_client.py
vectorvein/chat_clients/gemini_client.py
vectorvein/chat_clients/groq_client.py
vectorvein/chat_clients/local_client.py
vectorvein/chat_clients/minimax_client.py
vectorvein/chat_clients/mistral_client.py
vectorvein/chat_clients/moonshot_client.py
vectorvein/chat_clients/openai_client.py
vectorvein/chat_clients/openai_compatible_client.py
vectorvein/chat_clients/py.typed
vectorvein/chat_clients/qwen_client.py
vectorvein/chat_clients/stepfun_client.py
vectorvein/chat_clients/utils.py
vectorvein/chat_clients/xai_client.py
vectorvein/chat_clients/yi_client.py
vectorvein/chat_clients/zhipuai_client.py
vectorvein/py.typed
vectorvein/server/token_server.py
vectorvein/settings/__init__.py
vectorvein/settings/py.typed
vectorvein/types/__init__.py
vectorvein/types/defaults.py
vectorvein/types/enums.py
vectorvein/types/exception.py
vectorvein/types/llm_parameters.py
vectorvein/types/py.typed
vectorvein/types/settings.py
vectorvein/utilities/chunking.py
vectorvein/utilities/gcp_token.py
vectorvein/utilities/media_processing.py
vectorvein/utilities/rate_limiter.py
vectorvein/utilities/retry.py
vectorvein/workflow/graph/edge.py
vectorvein/workflow/graph/node.py
vectorvein/workflow/graph/port.py
vectorvein/workflow/graph/workflow.py
vectorvein/workflow/nodes/__init__.py
vectorvein/workflow/nodes/audio_generation.py
vectorvein/workflow/nodes/cloud_storage.py
vectorvein/workflow/nodes/control_flows.py
vectorvein/workflow/nodes/file_processing.py
vectorvein-0.3.68.dist-info/RECORD
