Metadata-Version: 2.1
Name: vectorvein
Version: 0.3.68
Summary: VectorVein Python SDK
Author-Email: Anderson <andersonby@163.com>
License: MIT
Requires-Python: >=3.10
Requires-Dist: openai>=1.99.3
Requires-Dist: tiktoken>=0.7.0
Requires-Dist: httpx>=0.27.0
Requires-Dist: anthropic>=0.47.1
Requires-Dist: pydantic>=2.8.2
Requires-Dist: Pillow>=10.4.0
Requires-Dist: deepseek-tokenizer>=0.1.0
Requires-Dist: qwen-tokenizer>=0.2.0
Requires-Dist: pycryptodome>=3.21.0
Provides-Extra: bedrock
Requires-Dist: boto3>=1.28.57; extra == "bedrock"
Requires-Dist: botocore>=1.31.57; extra == "bedrock"
Provides-Extra: diskcache
Requires-Dist: diskcache; extra == "diskcache"
Provides-Extra: redis
Requires-Dist: redis; extra == "redis"
Provides-Extra: server
Requires-Dist: fastapi; extra == "server"
Requires-Dist: uvicorn; extra == "server"
Provides-Extra: vertex
Requires-Dist: google-auth>=2.35.0; extra == "vertex"
